DatabricksSparkReferenceApplications/README.md
DatabricksSparkReferenceApplications/__init__.py
DatabricksSparkReferenceApplications/__main__.py
DatabricksSparkReferenceApplications/file.epub
DatabricksSparkReferenceApplications/index.html
DatabricksSparkReferenceApplications/css/__init__.py
DatabricksSparkReferenceApplications/css/annotations.css
DatabricksSparkReferenceApplications/css/main.css
DatabricksSparkReferenceApplications/css/normalize.css
DatabricksSparkReferenceApplications/css/popup.css
DatabricksSparkReferenceApplications/font/__init__.py
DatabricksSparkReferenceApplications/font/fontello.eot
DatabricksSparkReferenceApplications/font/fontello.svg
DatabricksSparkReferenceApplications/font/fontello.ttf
DatabricksSparkReferenceApplications/font/fontello.woff
DatabricksSparkReferenceApplications/img/__init__.py
DatabricksSparkReferenceApplications/img/annotator-glyph-sprite.png
DatabricksSparkReferenceApplications/img/annotator-icon-sprite.png
DatabricksSparkReferenceApplications/img/apple-touch-icon.png
DatabricksSparkReferenceApplications/img/cancelfullscreen.png
DatabricksSparkReferenceApplications/img/close.png
DatabricksSparkReferenceApplications/img/fullscreen.png
DatabricksSparkReferenceApplications/img/loader.gif
DatabricksSparkReferenceApplications/img/menu-icon.png
DatabricksSparkReferenceApplications/img/save.png
DatabricksSparkReferenceApplications/img/saved.png
DatabricksSparkReferenceApplications/img/settings-s.png
DatabricksSparkReferenceApplications/img/settings.png
DatabricksSparkReferenceApplications/img/star.png
DatabricksSparkReferenceApplications/js/__init__.py
DatabricksSparkReferenceApplications/js/epub.js
DatabricksSparkReferenceApplications/js/epub.min.js
DatabricksSparkReferenceApplications/js/epub.min.map
DatabricksSparkReferenceApplications/js/hooks.min.js
DatabricksSparkReferenceApplications/js/hooks.min.map
DatabricksSparkReferenceApplications/js/reader.js
DatabricksSparkReferenceApplications/js/reader.js.map
databricks_spark_reference_applications-2024.3.2.0.dist-info/METADATA
databricks_spark_reference_applications-2024.3.2.0.dist-info/WHEEL
databricks_spark_reference_applications-2024.3.2.0.dist-info/entry_points.txt
databricks_spark_reference_applications-2024.3.2.0.dist-info/top_level.txt
databricks_spark_reference_applications-2024.3.2.0.dist-info/RECORD
